persistence.py
mindpowered_persistence/Persistence.py
mindpowered_persistence/__init__.py
mindpowered_persistence-0.1.3.dist-info/LICENSE.txt
mindpowered_persistence-0.1.3.dist-info/METADATA
mindpowered_persistence-0.1.3.dist-info/WHEEL
mindpowered_persistence-0.1.3.dist-info/top_level.txt
mindpowered_persistence-0.1.3.dist-info/RECORD
