Metadata-Version: 2.1
Name: mindpowered-persistence
Version: 0.1.3
Summary: Persistence
Home-page: https://mindpowered.dev/
Author: Mind Powered Corporation
Author-email: support@mindpowered.dev
License: CPAL-1.0
Platform: UNKNOWN
Classifier: Programming Language :: Python :: 3
Classifier: Operating System :: OS Independent
Requires-Dist: mindpowered-maglev
